usrl_colormaps/__init__.py
usrl_colormaps-1.0.0.dist-info/WHEEL
usrl_colormaps-1.0.0.dist-info/METADATA
usrl_colormaps-1.0.0.dist-info/RECORD
