Metadata-Version: 2.1
Name: usrl-colormaps
Version: 1.0.0
Summary: Matolotlib colormaps for the Uppsala Social Robotics Lab.
Author: Sebastian Wallkötter
Author-email: sebastian.wallkotter@it.uu.se
Requires-Python: >=3.7
Classifier: Programming Language :: Python :: 3
Classifier: Programming Language :: Python :: 3.10
Classifier: Programming Language :: Python :: 3.7
Classifier: Programming Language :: Python :: 3.8
Classifier: Programming Language :: Python :: 3.9
Requires-Dist: numpy (>=1.20,<2.0)
